fastquadtree/__init__.py
fastquadtree/_base_quadtree.py
fastquadtree/_base_quadtree_objects.py
fastquadtree/_common.py
fastquadtree/_insert_result.py
fastquadtree/_item.py
fastquadtree/_native.abi3.so
fastquadtree/_obj_store.py
fastquadtree/point_quadtree.py
fastquadtree/point_quadtree_objects.py
fastquadtree/py.typed
fastquadtree/pyqtree.py
fastquadtree/rect_quadtree.py
fastquadtree/rect_quadtree_objects.py
fastquadtree-2.1.1.dist-info/METADATA
fastquadtree-2.1.1.dist-info/WHEEL
fastquadtree-2.1.1.dist-info/licenses/LICENSE
fastquadtree-2.1.1.dist-info/RECORD
